.DS_Store
lmpylib/__init__.py
lmpylib/bits.py
lmpylib/byteutil.py
lmpylib/core.py
lmpylib/cv.py
lmpylib/geo.py
lmpylib/nlp.py
lmpylib/sigproc.py
lmpylib/version.py
lmpylib_mingsqtt-1.0.8.dist-info/LICENSE
lmpylib_mingsqtt-1.0.8.dist-info/METADATA
lmpylib_mingsqtt-1.0.8.dist-info/WHEEL
lmpylib_mingsqtt-1.0.8.dist-info/top_level.txt
lmpylib_mingsqtt-1.0.8.dist-info/RECORD
