Metadata-Version: 2.1
Name: lmpylib-mingsqtt
Version: 1.0.8
Summary: This is a personal library.
Home-page: https://github.com/mingsqtt/lmpylib-proj
Author: Li Ming
Author-email: mingsqtt@hotmail.com
License: UNKNOWN
Platform: UNKNOWN
Classifier: Programming Language :: Python :: 3
Classifier: License :: OSI Approved :: MIT License
Classifier: Operating System :: OS Independent
Requires-Python: >=3.6
